django_htmx_utils/__init__.py
django_htmx_utils/events.py
django_htmx_utils-0.0.1.dist-info/LICENSE
django_htmx_utils-0.0.1.dist-info/METADATA
django_htmx_utils-0.0.1.dist-info/WHEEL
django_htmx_utils-0.0.1.dist-info/top_level.txt
django_htmx_utils-0.0.1.dist-info/RECORD
